visualmation/__init__.py
visualmation/main.py
visualmation-0.0.1.dist-info/LICENSE
visualmation-0.0.1.dist-info/METADATA
visualmation-0.0.1.dist-info/WHEEL
visualmation-0.0.1.dist-info/RECORD
