Metadata-Version: 2.1
Name: visualmation
Version: 0.0.1
Summary: computer graphics animation engine
Home-page: https://github.com/luzhixing12345/visualmation
License: MIT
Author: luzhixing12345
Author-email: luzhixing12345@163.com
Requires-Python: >=3.7,<4.0
Classifier: License :: OSI Approved :: MIT License
Classifier: Programming Language :: Python :: 3
Classifier: Programming Language :: Python :: 3.7
Classifier: Programming Language :: Python :: 3.8
Classifier: Programming Language :: Python :: 3.9
Classifier: Programming Language :: Python :: 3.10
Classifier: Programming Language :: Python :: 3.11
Project-URL: Documentation, https://luzhixing12345.github.io/visualmation/
Project-URL: Repository, https://github.com/luzhixing12345/visualmation
